pysvg/__init__.py
pysvg/constants.py
pysvg/globals.py
pysvg/logger.py
pysvg/components/__init__.py
pysvg/components/base.py
pysvg/components/canvas.py
pysvg/components/cell.py
pysvg/components/circle.py
pysvg/components/content.py
pysvg/components/ellipse.py
pysvg/components/line.py
pysvg/components/matrix.py
pysvg/components/polyline.py
pysvg/components/rectangle.py
pysvg/schema/__init__.py
pysvg/schema/bbox.py
pysvg/schema/color.py
pysvg/schema/svg_config.py
pysvg/utils/__init__.py
pysvg/utils/iterator.py
pysvg/utils/list.py
pysvg/utils/matrix.py
pysvg/utils/misc.py
pysvg/utils/path.py
svg_python-0.0.10.dist-info/METADATA
svg_python-0.0.10.dist-info/WHEEL
svg_python-0.0.10.dist-info/licenses/LICENSE
svg_python-0.0.10.dist-info/RECORD
