Metadata-Version: 2.4
Name: svg-python
Version: 0.0.10
License: 
License-File: LICENSE
Requires-Python: >=3.10
Requires-Dist: colorama>=0.4.6
Requires-Dist: pydantic>=2.11.5
Requires-Dist: typing-extensions>=4.14.0
Provides-Extra: test
Requires-Dist: pytest>=8.4.0; extra == 'test'
